foolsr/__init__.py
foolsr/cli.py
foolsr/example.py
foolsr-1.0.0.dist-info/licenses/LICENSE
foolsr-1.0.0.dist-info/METADATA
foolsr-1.0.0.dist-info/WHEEL
foolsr-1.0.0.dist-info/entry_points.txt
foolsr-1.0.0.dist-info/top_level.txt
foolsr-1.0.0.dist-info/RECORD
