Metadata-Version: 2.4
Name: foolsr
Version: 1.0.0
Summary: A small toolset for small stuff I do.
Author-email: Walper <MrWalper@proton.me>
License-Expression: GPL-3.0-only
Project-URL: Homepage, https://github.com/MrGaffiot/funny-toolbox-recode
Project-URL: Issues, https://github.com/MrGaffiot/funny-toolbox-recode/issues
Classifier: Programming Language :: Python :: 3
Classifier: Operating System :: OS Independent
Requires-Python: >=3.9
License-File: LICENSE
Dynamic: license-file
